{"assets":{"22FFA14BA7BB6229D12D5AB4E547D6F5":{"type":"texture","index":1,"assetRequest":{"type":"slide","state":"contents","slide":"none"},"url":{"native":"assets\/C8A08468-AF78-46AB-868F-D3F2C612D8D8.pdf"},"width":1920,"height":1080},"42BEF8067900DC10664435D0250BA034":{"type":"texture","index":0,"assetRequest":{"type":"slide","state":"contents","slide":"none"},"url":{"native":"assets\/C8A08468-AF78-46AB-868F-D3F2C612D8D8.pdf"},"width":1920,"height":1080}},"events":[{"effects":[{"beginTime":0,"baseLayer":{"animations":[],"initialState":{"affineTransform":[1,0,0,1,0,0],"masksToBounds":false,"rotation":0,"scale":1,"position":{"pointX":960,"pointY":540},"width":1920,"sublayerTransform":[1,0,0,0,0,1,0,0,0,0,1,0,0,0,0,1],"contentsRect":{"y":0,"x":0,"width":1,"height":1},"opacity":1,"edgeAntialiasingMask":251658240,"height":1080,"hidden":false,"anchorPoint":{"pointX":0.5,"pointY":0.5}},"objectID":"0","layers":[{"animations":[],"initialState":{"affineTransform":[1,0,0,1,0,0],"masksToBounds":false,"rotation":0,"scale":1,"position":{"pointX":960,"pointY":540},"width":1920,"sublayerTransform":[1,0,0,0,0,1,0,0,0,0,1,-0.00035007912466775983,0,0,0,1],"contentsRect":{"y":0,"x":0,"width":1,"height":1},"opacity":1,"edgeAntialiasingMask":251658240,"height":1080,"hidden":false,"anchorPoint":{"pointX":0.5,"pointY":0.5}},"layers":[{"animations":[],"layers":[],"texturedRectangle":{"isBackgroundTexture":false,"singleTextureOpacity":1,"textureType":0,"textBaseline":0,"textXHeight":0,"isVerticalText":false},"initialState":{"affineTransform":[1,0,0,1,0,0],"masksToBounds":false,"rotation":0,"scale":1,"position":{"pointX":960,"pointY":540},"width":1920,"sublayerTransform":[1,0,0,0,0,1,0,0,0,0,1,0,0,0,0,1],"contentsRect":{"y":0,"x":0,"width":1,"height":1},"opacity":1,"edgeAntialiasingMask":0,"height":1080,"hidden":false,"anchorPoint":{"pointX":0.5,"pointY":0.5}},"texture":"22FFA14BA7BB6229D12D5AB4E547D6F5"},{"animations":[{"timeOffset":0,"from":{"scalar":false},"beginTime":0,"repeatCount":0,"fillMode":"both","property":"hidden","autoreverses":false,"duration":0.01,"to":{"scalar":true}}],"layers":[],"texturedRectangle":{"isBackgroundTexture":false,"singleTextureOpacity":1,"textureType":0,"textBaseline":0,"textXHeight":0,"isVerticalText":false},"initialState":{"affineTransform":[1,0,0,1,0,0],"masksToBounds":false,"rotation":0,"scale":1,"position":{"pointX":960,"pointY":540},"width":1920,"sublayerTransform":[1,0,0,0,0,1,0,0,0,0,1,0,0,0,0,1],"contentsRect":{"y":0,"x":0,"width":1,"height":1},"opacity":1,"edgeAntialiasingMask":0,"height":1080,"hidden":false,"anchorPoint":{"pointX":0.5,"pointY":0.5}},"texture":"42BEF8067900DC10664435D0250BA034"}]}]},"effects":[],"duration":0.01,"type":"transition","name":"none","objectID":"0"}],"automaticPlay":false,"hyperlinks":[{"url":"https:\/\/vimeo.com\/318167458","targetRectangle":{"y":456.12499237060547,"x":1477.1558837890625,"width":172,"height":167.75671631097794}},{"url":"https:\/\/www.youtube.com\/watch?v=iJpZPjxhKgE","targetRectangle":{"y":456.12499237060547,"x":873.09375,"width":172,"height":167.75671631097794}},{"url":"https:\/\/www.youtube.com\/watch?v=3k5cy7VH1es","targetRectangle":{"y":456.12499237060547,"x":269.93792057037354,"width":172,"height":167.75671631097794}}],"accessibility":[{"text":"play-button-transparent-png-3.png","targetRectangle":{"y":456.12499237060547,"x":1477.1558837890625,"width":172,"height":167.75671631097794}},{"text":"play-button-transparent-png-3.png","targetRectangle":{"y":456.12499237060547,"x":873.09375,"width":172,"height":167.75671631097794}},{"text":"play-button-transparent-png-3.png","targetRectangle":{"y":456.12499237060547,"x":269.93792057037354,"width":172,"height":167.75671631097794}},{"text":"Zrzut ekranu 2019-03-25 o 16.35.17.png","targetRectangle":{"y":379.73437499999994,"x":706.74998474121094,"width":504.6875,"height":320.53390502929693}},{"text":"REFERENCES","targetRectangle":{"y":79.44669508934021,"x":79.964148044586182,"width":351.51999999999992,"height":62.49163818359375}},{"text":"FORM - YELLOW WORLD","targetRectangle":{"y":143.44669508934021,"x":79.964148044586182,"width":306.0499999999999,"height":29.274826049804688}},{"text":"Zrzut ekranu 2019-03-25 o 15.10.58.png","targetRectangle":{"y":378.56250000000006,"x":1309.6401901245117,"width":507.03125,"height":322.87499999999994}},{"text":"Zrzut ekranu 2019-03-25 o 16.33.47.png","targetRectangle":{"y":379.40625000000011,"x":103.32854080200195,"width":505.21875,"height":321.20028686523438}},{"text":"Zrzut ekranu 2019-03-20 o 20.29.07.png","targetRectangle":{"y":0.014404296875,"x":-7.62939453125e-06,"width":1920,"height":1079.9712127447128}}],"baseLayer":{"animations":[],"initialState":{"affineTransform":[1,0,0,1,0,0],"masksToBounds":false,"rotation":0,"scale":1,"position":{"pointX":960,"pointY":540},"width":1920,"sublayerTransform":[1,0,0,0,0,1,0,0,0,0,1,0,0,0,0,1],"contentsRect":{"y":0,"x":0,"width":1,"height":1},"opacity":1,"edgeAntialiasingMask":251658240,"height":1080,"hidden":false,"anchorPoint":{"pointX":0.5,"pointY":0.5}},"objectID":"0","layers":[{"animations":[],"initialState":{"affineTransform":[1,0,0,1,0,0],"masksToBounds":false,"rotation":0,"scale":1,"position":{"pointX":960,"pointY":540},"width":1920,"sublayerTransform":[1,0,0,0,0,1,0,0,0,0,1,-0.00035007912466775983,0,0,0,1],"contentsRect":{"y":0,"x":0,"width":1,"height":1},"opacity":1,"edgeAntialiasingMask":251658240,"height":1080,"hidden":false,"anchorPoint":{"pointX":0.5,"pointY":0.5}},"layers":[{"animations":[],"layers":[],"texturedRectangle":{"isBackgroundTexture":false,"singleTextureOpacity":1,"textureType":0,"textBaseline":0,"textXHeight":0,"isVerticalText":false},"initialState":{"affineTransform":[1,0,0,1,0,0],"masksToBounds":false,"rotation":0,"scale":1,"position":{"pointX":960,"pointY":540},"width":1920,"sublayerTransform":[1,0,0,0,0,1,0,0,0,0,1,0,0,0,0,1],"contentsRect":{"y":0,"x":0,"width":1,"height":1},"opacity":1,"edgeAntialiasingMask":0,"height":1080,"hidden":false,"anchorPoint":{"pointX":0.5,"pointY":0.5}},"texture":"42BEF8067900DC10664435D0250BA034"}]}]}}]}