{"assets":{"431853571F491B4AA18E2455B1C27A79":{"type":"texture","index":1,"assetRequest":{"type":"slide","state":"contents","slide":"none"},"url":{"native":"assets\/C6A32764-9F93-4370-A742-535A02B16B17.pdf"},"width":1920,"height":1080},"E487B62D572A84D09F44E1CDBFBAA159":{"type":"texture","index":0,"assetRequest":{"type":"slide","state":"contents","slide":"none"},"url":{"native":"assets\/C6A32764-9F93-4370-A742-535A02B16B17.pdf"},"width":1920,"height":1080}},"events":[{"effects":[{"beginTime":0,"baseLayer":{"animations":[],"initialState":{"affineTransform":[1,0,0,1,0,0],"masksToBounds":false,"rotation":0,"scale":1,"position":{"pointX":960,"pointY":540},"width":1920,"sublayerTransform":[1,0,0,0,0,1,0,0,0,0,1,0,0,0,0,1],"contentsRect":{"y":0,"x":0,"width":1,"height":1},"opacity":1,"edgeAntialiasingMask":251658240,"height":1080,"hidden":false,"anchorPoint":{"pointX":0.5,"pointY":0.5}},"objectID":"0","layers":[{"animations":[],"initialState":{"affineTransform":[1,0,0,1,0,0],"masksToBounds":false,"rotation":0,"scale":1,"position":{"pointX":960,"pointY":540},"width":1920,"sublayerTransform":[1,0,0,0,0,1,0,0,0,0,1,-0.00035007912466775983,0,0,0,1],"contentsRect":{"y":0,"x":0,"width":1,"height":1},"opacity":1,"edgeAntialiasingMask":251658240,"height":1080,"hidden":false,"anchorPoint":{"pointX":0.5,"pointY":0.5}},"layers":[{"animations":[],"layers":[],"texturedRectangle":{"isBackgroundTexture":false,"singleTextureOpacity":1,"textureType":0,"textBaseline":0,"textXHeight":0,"isVerticalText":false},"initialState":{"affineTransform":[1,0,0,1,0,0],"masksToBounds":false,"rotation":0,"scale":1,"position":{"pointX":960,"pointY":540},"width":1920,"sublayerTransform":[1,0,0,0,0,1,0,0,0,0,1,0,0,0,0,1],"contentsRect":{"y":0,"x":0,"width":1,"height":1},"opacity":1,"edgeAntialiasingMask":0,"height":1080,"hidden":false,"anchorPoint":{"pointX":0.5,"pointY":0.5}},"texture":"431853571F491B4AA18E2455B1C27A79"},{"animations":[{"timeOffset":0,"from":{"scalar":false},"beginTime":0,"repeatCount":0,"fillMode":"both","property":"hidden","autoreverses":false,"duration":0.01,"to":{"scalar":true}}],"layers":[],"texturedRectangle":{"isBackgroundTexture":false,"singleTextureOpacity":1,"textureType":0,"textBaseline":0,"textXHeight":0,"isVerticalText":false},"initialState":{"affineTransform":[1,0,0,1,0,0],"masksToBounds":false,"rotation":0,"scale":1,"position":{"pointX":960,"pointY":540},"width":1920,"sublayerTransform":[1,0,0,0,0,1,0,0,0,0,1,0,0,0,0,1],"contentsRect":{"y":0,"x":0,"width":1,"height":1},"opacity":1,"edgeAntialiasingMask":0,"height":1080,"hidden":false,"anchorPoint":{"pointX":0.5,"pointY":0.5}},"texture":"E487B62D572A84D09F44E1CDBFBAA159"}]}]},"effects":[],"duration":0.01,"type":"transition","name":"none","objectID":"0"}],"automaticPlay":false,"hyperlinks":[{"url":"https:\/\/vimeo.com\/trojnar","targetRectangle":{"y":907.51084136962891,"x":1285.8771667480469,"width":163.41363668441772,"height":159.38218384981155}},{"url":"https:\/\/vimeo.com\/kajetanplis","targetRectangle":{"y":907.51084136962891,"x":1753.8771667480469,"width":163.41363668441772,"height":159.38218384981155}},{"url":"https:\/\/vimeo.com\/uznanski","targetRectangle":{"y":907.51084136962891,"x":281.87715911865234,"width":163.41363668441772,"height":159.38218384981155}},{"url":"https:\/\/vimeo.com\/user9141273","targetRectangle":{"y":907.51084136962891,"x":817.87716674804688,"width":163.41363668441772,"height":159.38218384981155}}],"accessibility":[{"text":"265292_10151156324814596_595750983_o.jpg","targetRectangle":{"y":1.1368683772161603e-13,"x":990.02413940429688,"width":468.10443621447484,"height":1080}},{"text":"24883493_813132765542282_7027516848459022571_o.jpg","targetRectangle":{"y":-1.083984375,"x":-2.794708251953125,"width":459.62667465209961,"height":1082.1679830551147}},{"text":"play-button-transparent-png-3.png","targetRectangle":{"y":907.51084136962891,"x":1285.8771667480469,"width":163.41363668441772,"height":159.38218384981155}},{"text":"24879818_813132635542295_1954471086147573279_o.jpg","targetRectangle":{"y":-3.3750839233398438,"x":1457.7598876953125,"width":463.84990215301514,"height":1086.7525339126587}},{"text":"play-button-transparent-png-3.png","targetRectangle":{"y":907.51084136962891,"x":1753.8771667480469,"width":163.41363668441772,"height":159.38218384981155}},{"text":"play-button-transparent-png-3.png","targetRectangle":{"y":907.51084136962891,"x":281.87715911865234,"width":163.41363668441772,"height":159.38218384981155}},{"text":"play-button-transparent-png-3.png","targetRectangle":{"y":907.51084136962891,"x":817.87716674804688,"width":163.41363668441772,"height":159.38218384981155}},{"text":"Zrzut ekranu 2019-03-27 o 07.37.21.png","targetRectangle":{"y":0.125,"x":-0.6875,"width":1921.3890657084994,"height":1079.75}},{"text":"12621964_10153301472587761_5470411219674921520_o.jpg","targetRectangle":{"y":0.31250953674316406,"x":456.93609619140625,"width":537.6875,"height":1079.3786716461182}}],"baseLayer":{"animations":[],"initialState":{"affineTransform":[1,0,0,1,0,0],"masksToBounds":false,"rotation":0,"scale":1,"position":{"pointX":960,"pointY":540},"width":1920,"sublayerTransform":[1,0,0,0,0,1,0,0,0,0,1,0,0,0,0,1],"contentsRect":{"y":0,"x":0,"width":1,"height":1},"opacity":1,"edgeAntialiasingMask":251658240,"height":1080,"hidden":false,"anchorPoint":{"pointX":0.5,"pointY":0.5}},"objectID":"0","layers":[{"animations":[],"initialState":{"affineTransform":[1,0,0,1,0,0],"masksToBounds":false,"rotation":0,"scale":1,"position":{"pointX":960,"pointY":540},"width":1920,"sublayerTransform":[1,0,0,0,0,1,0,0,0,0,1,-0.00035007912466775983,0,0,0,1],"contentsRect":{"y":0,"x":0,"width":1,"height":1},"opacity":1,"edgeAntialiasingMask":251658240,"height":1080,"hidden":false,"anchorPoint":{"pointX":0.5,"pointY":0.5}},"layers":[{"animations":[],"layers":[],"texturedRectangle":{"isBackgroundTexture":false,"singleTextureOpacity":1,"textureType":0,"textBaseline":0,"textXHeight":0,"isVerticalText":false},"initialState":{"affineTransform":[1,0,0,1,0,0],"masksToBounds":false,"rotation":0,"scale":1,"position":{"pointX":960,"pointY":540},"width":1920,"sublayerTransform":[1,0,0,0,0,1,0,0,0,0,1,0,0,0,0,1],"contentsRect":{"y":0,"x":0,"width":1,"height":1},"opacity":1,"edgeAntialiasingMask":0,"height":1080,"hidden":false,"anchorPoint":{"pointX":0.5,"pointY":0.5}},"texture":"E487B62D572A84D09F44E1CDBFBAA159"}]}]}}]}